lazyprofiler/GetStats.py
lazyprofiler/__init__.py
lazyprofiler/__main__.py
lazyprofiler/_version.py
lazyprofiler/cli.py
lazyprofiler-0.1.1.dist-info/LICENSE
lazyprofiler-0.1.1.dist-info/METADATA
lazyprofiler-0.1.1.dist-info/WHEEL
lazyprofiler-0.1.1.dist-info/entry_points.txt
lazyprofiler-0.1.1.dist-info/top_level.txt
lazyprofiler-0.1.1.dist-info/RECORD
